aatps/__init__.py
aatps/admin.py
aatps/app_settings.py
aatps/apps.py
aatps/auth_hooks.py
aatps/esi.py
aatps/models.py
aatps/tasks.py
aatps/urls.py
aatps/utils.py
aatps/views.py
aatps/locale/.gitkeep
aatps/management/__init__.py
aatps/management/commands/__init__.py
aatps/management/commands/aa_tps_pull.py
aatps/management/commands/aa_tps_setup.py
aatps/migrations/0001_initial.py
aatps/migrations/0002_campaignkillmail_ship_type_id_and_more.py
aatps/migrations/0003_campaignkillmail_ship_group_name.py
aatps/migrations/0004_campaignkillmail_final_blow_alliance_id_and_more.py
aatps/migrations/0005_campaign_last_run.py
aatps/migrations/0006_add_monthly_killmail_models.py
aatps/migrations/0007_migrate_campaign_killmails.py
aatps/migrations/0008_remove_legacy_models.py
aatps/migrations/0009_add_performance_indexes.py
aatps/migrations/0010_update_unique_constraint.py
aatps/migrations/__init__.py
aatps/static/aatps/.gitkeep
aatps/static/aatps/css/dashboard.css
aatps/static/aatps/js/dashboard.js
aatps/templates/aatps/base.html
aatps/templates/aatps/dashboard.html
aatps/tests/__init__.py
aatps/tests/factories.py
aatps/tests/test_aatps.py
aatps/tests/test_utils.py
aatps/tests/test_views.py
aa_tps-1.1.2.dist-info/METADATA
aa_tps-1.1.2.dist-info/WHEEL
aa_tps-1.1.2.dist-info/licenses/LICENSE
aa_tps-1.1.2.dist-info/RECORD
