Metadata-Version: 2.4
Name: aa-tps
Version: 1.1.2
Summary: Total Participation Statistics for Alliance Auth
Project-URL: Changelog, https://github.com/BroodLK/aa-tps/blob/master/CHANGELOG.md
Project-URL: Tracker, https://github.com/BroodLK/aa-tps/issues
Author-email: BioBrute <broodlk@gmail.com>
License:                     GNU GENERAL PUBLIC LICENSE
License-File: LICENSE
Keywords: allianceauth,killboard,pvp,statistics,zkillboard
Classifier: Environment :: Web Environment
Classifier: Framework :: Django
Classifier: Framework :: Django :: 4.2
Classifier: Intended Audience :: Developers
Classifier: License :: OSI Approved :: GNU General Public License v3 (GPLv3)
Classifier: Operating System :: OS Independent
Classifier: Programming Language :: Python
Classifier: Programming Language :: Python :: 3 :: Only
Classifier: Programming Language :: Python :: 3.10
Classifier: Programming Language :: Python :: 3.11
Classifier: Programming Language :: Python :: 3.12
Classifier: Programming Language :: Python :: 3.13
Classifier: Topic :: Internet :: WWW/HTTP
Classifier: Topic :: Internet :: WWW/HTTP :: Dynamic Content
Requires-Python: <3.14,>=3.10
Requires-Dist: allianceauth<5,>=4.3.1
Requires-Dist: django-eveuniverse
